cryptofeed/__init__.py
cryptofeed/callback.py
cryptofeed/config.py
cryptofeed/connection.py
cryptofeed/connection_handler.py
cryptofeed/defines.py
cryptofeed/exceptions.py
cryptofeed/exchange.py
cryptofeed/feed.py
cryptofeed/feedhandler.py
cryptofeed/log.py
cryptofeed/nbbo.py
cryptofeed/raw_data_collection.py
cryptofeed/symbols.py
cryptofeed/types.cp39-win_amd64.pyd
cryptofeed/backends/__init__.py
cryptofeed/backends/_util.py
cryptofeed/backends/aggregate.py
cryptofeed/backends/arctic.py
cryptofeed/backends/backend.py
cryptofeed/backends/gcppubsub.py
cryptofeed/backends/http.py
cryptofeed/backends/influxdb.py
cryptofeed/backends/kafka.py
cryptofeed/backends/mongo.py
cryptofeed/backends/postgres.py
cryptofeed/backends/quest.py
cryptofeed/backends/rabbitmq.py
cryptofeed/backends/redis.py
cryptofeed/backends/socket.py
cryptofeed/backends/zmq.py
cryptofeed/exchanges/__init__.py
cryptofeed/exchanges/ascendex.py
cryptofeed/exchanges/ascendex_futures.py
cryptofeed/exchanges/bequant.py
cryptofeed/exchanges/binance.py
cryptofeed/exchanges/binance_delivery.py
cryptofeed/exchanges/binance_futures.py
cryptofeed/exchanges/binance_us.py
cryptofeed/exchanges/bitdotcom.py
cryptofeed/exchanges/bitfinex.py
cryptofeed/exchanges/bitflyer.py
cryptofeed/exchanges/bitget.py
cryptofeed/exchanges/bithumb.py
cryptofeed/exchanges/bitmex.py
cryptofeed/exchanges/bitstamp.py
cryptofeed/exchanges/bittrex.py
cryptofeed/exchanges/blockchain.py
cryptofeed/exchanges/bybit.py
cryptofeed/exchanges/coinbase.py
cryptofeed/exchanges/cryptodotcom.py
cryptofeed/exchanges/delta.py
cryptofeed/exchanges/deribit.py
cryptofeed/exchanges/dydx.py
cryptofeed/exchanges/exx.py
cryptofeed/exchanges/fmfw.py
cryptofeed/exchanges/ftx.py
cryptofeed/exchanges/ftx_tr.py
cryptofeed/exchanges/ftx_us.py
cryptofeed/exchanges/gateio.py
cryptofeed/exchanges/gemini.py
cryptofeed/exchanges/hitbtc.py
cryptofeed/exchanges/huobi.py
cryptofeed/exchanges/huobi_dm.py
cryptofeed/exchanges/huobi_swap.py
cryptofeed_tks-2.3.0.dist-info/AUTHORS.md
cryptofeed_tks-2.3.0.dist-info/LICENSE
cryptofeed_tks-2.3.0.dist-info/METADATA
cryptofeed_tks-2.3.0.dist-info/WHEEL
cryptofeed_tks-2.3.0.dist-info/top_level.txt
cryptofeed_tks-2.3.0.dist-info/RECORD
